["{\"id\":\"2019-12\",\"classNumber\":{\"grade\":1,\"program\":\"1\",\"formerClass\":false},\"date\":\"2019-12-05\",\"periods\":[1,2],\"className\":\"基礎数学\",\"teacher\":\"吉田\",\"note\":\"補講実施予定\"}", "{\"id\":\"2019-12\",\"classNumber\":{\"grade\":4,\"program\":\"S\",\"formerClass\":false},\"date\":\"2019-12-05\",\"periods\":[3,4],\"className\":\"集合と位相\",\"teacher\":\"吉田\",\"note\":\"補講実施予定\"}", "{\"id\":\"2019-12\",\"classNumber\":{\"grade\":1,\"program\":\"3\",\"formerClass\":false},\"date\":\"2019-12-12\",\"periods\":[3,4],\"className\":\"情報リテラシー\",\"teacher\":\"竹谷\",\"note\":\"12月20日(金) [7・8限] に補講実施\"}", "{\"id\":\"2019-12\",\"classNumber\":{\"grade\":2,\"program\":\"E\",\"formerClass\":false},\"date\":\"2019-12-16\",\"periods\":[3,4],\"className\":\"総合理工演習\",\"teacher\":\"原田\",\"note\":\"補講日に実施\"}", "{\"id\":\"2019-12\",\"classNumber\":{\"grade\":5,\"program\":\"E\",\"formerClass\":true},\"date\":\"2019-12-16\",\"periods\":[5,6],\"className\":\"電気電子材料\",\"teacher\":\"原田\",\"note\":\"補講日に実施\"}", "{\"id\":\"2019-12\",\"classNumber\":{\"grade\":4,\"program\":\"C\",\"formerClass\":false},\"date\":\"2019-12-18\",\"periods\":[5,6],\"className\":\"応用数学II\",\"teacher\":\"宮﨑\",\"note\":\"補講日に実施\"}", "{\"id\":\"2019-12\",\"classNumber\":{\"grade\":3,\"program\":\"S\",\"formerClass\":false},\"date\":\"2019-12-19\",\"periods\":[1,2],\"className\":\"微分積分II\",\"teacher\":\"宮﨑\",\"note\":\"補講日に実施\"}", "{\"id\":\"2019-12\",\"classNumber\":{\"grade\":3,\"program\":\"E\",\"formerClass\":false},\"date\":\"2019-12-19\",\"periods\":[7,8],\"className\":\"計算科学\",\"teacher\":\"房\",\"note\":\"補講日に実施,CBT試験を実施\"}", "{\"id\":\"2019-12\",\"classNumber\":{\"grade\":1,\"program\":\"\",\"formerClass\":false},\"date\":\"2019-12-23\",\"periods\":[7,8],\"className\":\"日本会話と聴解I\",\"teacher\":\"杉山\",\"note\":\"補講日に実施\"}", "{\"id\":\"2019-12\",\"classNumber\":{\"grade\":1,\"program\":\"3\",\"formerClass\":false},\"date\":\"2019-12-23\",\"periods\":[5],\"className\":\"国語I\",\"teacher\":\"杉山\",\"note\":\"補講日に実施\"}"]